lehello.py
lehello-1.0.1a1.dist-info/METADATA
lehello-1.0.1a1.dist-info/RECORD
lehello-1.0.1a1.dist-info/WHEEL
lehello-1.0.1a1.dist-info/entry_points.txt
lehello-1.0.1a1.dist-info/top_level.txt
