Metadata-Version: 2.1
Name: lehello
Version: 1.0.1a1
Summary: Greeting plugin for the Le bot.
Home-page: https://github.com/cganterh/lehello
Author: Cristóbal Ganter
Author-email: cganterh@gmail.com
License: MIT
Keywords: python,python3,telegram-bot,chatbot
Platform: UNKNOWN
Classifier: Environment :: Web Environment
Classifier: Intended Audience :: System Administrators
Classifier: License :: OSI Approved :: MIT License
Classifier: Natural Language :: English
Classifier: Programming Language :: Python :: 3.5
Classifier: Programming Language :: Python :: 3.6
Classifier: Topic :: Communications :: Chat
Requires-Python: ~=3.5
Requires-Dist: python-telegram-bot (~=10.0)
